[[":bigint:572191161",{"type":"user","self":true,"contact":true,"mutualContact":true,"deleted":false,"bot":false,"botChatHistory":false,"botNochats":false,"verified":false,"restricted":false,"min":false,"botInlineGeo":false,"support":false,"scam":false,"applyMinPhoto":false,"fake":false,"id":"572191161","accessHash":"-5728582869403075915","firstName":"I'm Cyborg but It's Okay!","lastName":null,"username":"CYBORG_GIF","phone":"6281295026951","botInfoVersion":null,"botInlinePlaceholder":null,"langCode":null,"status":"online","photo":{"date":1700790241,"_":"chatPhoto","isBig":true,"dcId":5,"fileId":"AQADBQADt6cxG7nxGiIACAEABwMAA7nxGiIABLV610o7_H-wAAQeBA","uniqueFileId":"AQADt6cxG7nxGiI"},"dcId":5}],["CYBORG_GIF",{"type":"user","self":true,"contact":true,"mutualContact":true,"deleted":false,"bot":false,"botChatHistory":false,"botNochats":false,"verified":false,"restricted":false,"min":false,"botInlineGeo":false,"support":false,"scam":false,"applyMinPhoto":false,"fake":false,"id":"572191161","accessHash":"-5728582869403075915","firstName":"I'm Cyborg but It's Okay!","lastName":null,"username":"CYBORG_GIF","phone":"6281295026951","botInfoVersion":null,"botInlinePlaceholder":null,"langCode":null,"status":"online","photo":{"date":1700790241,"_":"chatPhoto","isBig":true,"dcId":5,"fileId":"AQADBQADt6cxG7nxGiIACAEABwMAA7nxGiIABLV610o7_H-wAAQeBA","uniqueFileId":"AQADt6cxG7nxGiI"},"dcId":5}],[":bigint:777000",{"type":"user","self":false,"contact":false,"mutualContact":false,"deleted":false,"bot":false,"botChatHistory":false,"botNochats":false,"verified":true,"restricted":false,"min":false,"botInlineGeo":false,"support":true,"scam":false,"applyMinPhoto":true,"fake":false,"id":"777000","accessHash":"-9034390846732262333","firstName":"Telegram","lastName":null,"username":null,"phone":"42777","botInfoVersion":null,"botInlinePlaceholder":null,"langCode":null,"status":"recently","photo":{"date":1700790241,"_":"chatPhoto","isBig":true,"dcId":1,"fileId":"AQADAQADsacxGyjbCwAJAQAHAwADKNsLAAVDpHsiZGWfggAEHgQ","uniqueFileId":"AQADsacxGyjbCwAB"},"dcId":1}],[":bigint:6293865566",{"type":"user","self":false,"contact":false,"mutualContact":false,"deleted":false,"bot":true,"botChatHistory":false,"botNochats":false,"verified":false,"restricted":false,"min":false,"botInlineGeo":false,"support":false,"scam":false,"applyMinPhoto":true,"fake":false,"id":"6293865566","accessHash":"1395906696482091280","firstName":"O Y E N N N","username":"ren_oyenn_bot","botInfoVersion":3,"photo":{"date":1700788162,"_":"chatPhoto","isBig":true,"dcId":5,"fileId":"AQADBQADkLoxGwPRIFUACAEABwMAA17EJHcBAAMQcWefvkFfEwAEHgQ","uniqueFileId":"AQADkLoxGwPRIFU"},"dcId":5}],["ren_oyenn_bot",{"type":"user","self":false,"contact":false,"mutualContact":false,"deleted":false,"bot":true,"botChatHistory":false,"botNochats":false,"verified":false,"restricted":false,"min":false,"botInlineGeo":false,"support":false,"scam":false,"applyMinPhoto":true,"fake":false,"id":"6293865566","accessHash":"1395906696482091280","firstName":"O Y E N N N","username":"ren_oyenn_bot","botInfoVersion":3,"photo":{"date":1700788162,"_":"chatPhoto","isBig":true,"dcId":5,"fileId":"AQADBQADkLoxGwPRIFUACAEABwMAA17EJHcBAAMQcWefvkFfEwAEHgQ","uniqueFileId":"AQADkLoxGwPRIFU"},"dcId":5}],[":bigint:-1001962626950",{"type":"supergroup","creator":true,"left":false,"broadcast":false,"verified":false,"megagroup":true,"restricted":false,"signatures":false,"min":false,"scam":false,"hasLink":false,"hasGeo":false,"slowmodeEnabled":false,"callActive":false,"callNotEmpty":false,"fake":false,"gigagroup":false,"noforward":false,"id":"-1001962626950","accessHash":"2729641022449182245","title":"O P A N K","adminRights":{"changeInfo":true,"postMessages":true,"editMessages":true,"deleteMessages":true,"banUsers":true,"inviteUsers":true,"pinMessages":true,"addAdmins":true,"anonymous":false,"manageCall":true,"other":true},"defaultBannedRights":{"viewMessages":false,"sendMessages":false,"sendMedia":false,"sendStickers":true,"sendGifs":false,"sendGames":false,"sendInline":false,"embedLinks":false,"sendPolls":false,"changeInfo":true,"inviteUsers":false,"pinMessages":false,"untilDate":2147483647},"photo":{"date":1700790217,"_":"chatPhoto","isBig":true,"dcId":5,"fileId":"AQADBQADh7sxG8kAAdlVAAgBAAcDAAN6oF-2Fv___yXmajMMouElAAQeBA","uniqueFileId":"AQADh7sxG8kAAdlV"},"dcId":5}],[":bigint:6443955175",{"type":"user","self":false,"contact":false,"mutualContact":false,"deleted":false,"bot":true,"botChatHistory":false,"botNochats":false,"verified":false,"restricted":false,"min":false,"botInlineGeo":false,"support":false,"scam":false,"applyMinPhoto":true,"fake":false,"id":"6443955175","accessHash":"6026446160424608331","firstName":"Choco Hidung Sobek","username":"ChocoKoecingBot","botInfoVersion":1,"photo":{"date":1700788194,"_":"chatPhoto","isBig":true,"dcId":5,"fileId":"AQADBQADf7gxGxHxoVUACAEABwMAA-fzFoABAANLIiB62jyiUwAEHgQ","uniqueFileId":"AQADf7gxGxHxoVU"},"dcId":5}],["ChocoKoecingBot",{"type":"user","self":false,"contact":false,"mutualContact":false,"deleted":false,"bot":true,"botChatHistory":false,"botNochats":false,"verified":false,"restricted":false,"min":false,"botInlineGeo":false,"support":false,"scam":false,"applyMinPhoto":true,"fake":false,"id":"6443955175","accessHash":"6026446160424608331","firstName":"Choco Hidung Sobek","username":"ChocoKoecingBot","botInfoVersion":1,"photo":{"date":1700788194,"_":"chatPhoto","isBig":true,"dcId":5,"fileId":"AQADBQADf7gxGxHxoVUACAEABwMAA-fzFoABAANLIiB62jyiUwAEHgQ","uniqueFileId":"AQADf7gxGxHxoVU"},"dcId":5}],[":bigint:-1001909548840",{"type":"supergroup","creator":true,"left":false,"broadcast":false,"verified":false,"megagroup":true,"restricted":false,"signatures":false,"min":false,"scam":false,"hasLink":false,"hasGeo":false,"slowmodeEnabled":false,"callActive":false,"callNotEmpty":false,"fake":false,"gigagroup":false,"noforward":false,"id":"-1001909548840","accessHash":"-7324308558427508628","title":"OYENNN","adminRights":{"changeInfo":true,"postMessages":true,"editMessages":true,"deleteMessages":true,"banUsers":true,"inviteUsers":true,"pinMessages":true,"addAdmins":true,"anonymous":false,"manageCall":true,"other":true},"defaultBannedRights":{"viewMessages":false,"sendMessages":false,"sendMedia":false,"sendStickers":false,"sendGifs":false,"sendGames":false,"sendInline":false,"embedLinks":false,"sendPolls":false,"changeInfo":true,"inviteUsers":false,"pinMessages":false,"untilDate":2147483647},"photo":{"date":1700788604,"_":"chatPhoto","isBig":true,"dcId":5,"fileId":"AQADBQADX7UxG8BW-FUACAEABwMAA9iIibkW____bDCTBSzUWpoABB4E","uniqueFileId":"AQADX7UxG8BW-FU"},"dcId":5}],[":bigint:637872952",{"type":"user","self":false,"contact":false,"mutualContact":false,"deleted":false,"bot":false,"botChatHistory":false,"botNochats":false,"verified":false,"restricted":false,"min":true,"botInlineGeo":false,"support":false,"scam":false,"applyMinPhoto":false,"fake":false,"id":"637872952","accessHash":"5891599155615247443","firstName":"Dennis","lastName":"_a.l","status":"recently","photo":{"date":1700788197,"_":"chatPhoto","isBig":true,"dcId":4,"fileId":"AQADBAADtqcxGzgrBSYACAEABwMAAzgrBSYABFMscI03KsNRAAQeBA","uniqueFileId":"AQADtqcxGzgrBSY"},"dcId":4}],[":bigint:-1001231457360",{"type":"supergroup","creator":false,"left":false,"broadcast":false,"verified":false,"megagroup":true,"restricted":false,"signatures":false,"min":true,"scam":false,"hasLink":false,"hasGeo":false,"slowmodeEnabled":false,"callActive":false,"callNotEmpty":false,"fake":false,"gigagroup":false,"noforward":false,"id":"-1001231457360","accessHash":"-4503642530566269911","title":"Xiaomi Mi 10 Series - Google Camera","username":"gcam_mi10","defaultBannedRights":{"viewMessages":false,"sendMessages":false,"sendMedia":false,"sendStickers":false,"sendGifs":false,"sendGames":false,"sendInline":false,"embedLinks":false,"sendPolls":true,"changeInfo":true,"inviteUsers":false,"pinMessages":true,"untilDate":2147483647},"photo":{"date":1700788197,"_":"chatPhoto","isBig":true,"dcId":4,"fileId":"AQADBAAD47UxGyXn2FMACAEABwMAA7Bj9OEW____KZRB0vrYf8EABB4E","uniqueFileId":"AQAD47UxGyXn2FM"},"dcId":4}],["gcam_mi10",{"type":"supergroup","creator":false,"left":false,"broadcast":false,"verified":false,"megagroup":true,"restricted":false,"signatures":false,"min":true,"scam":false,"hasLink":false,"hasGeo":false,"slowmodeEnabled":false,"callActive":false,"callNotEmpty":false,"fake":false,"gigagroup":false,"noforward":false,"id":"-1001231457360","accessHash":"-4503642530566269911","title":"Xiaomi Mi 10 Series - Google Camera","username":"gcam_mi10","defaultBannedRights":{"viewMessages":false,"sendMessages":false,"sendMedia":false,"sendStickers":false,"sendGifs":false,"sendGames":false,"sendInline":false,"embedLinks":false,"sendPolls":true,"changeInfo":true,"inviteUsers":false,"pinMessages":true,"untilDate":2147483647},"photo":{"date":1700788197,"_":"chatPhoto","isBig":true,"dcId":4,"fileId":"AQADBAAD47UxGyXn2FMACAEABwMAA7Bj9OEW____KZRB0vrYf8EABB4E","uniqueFileId":"AQAD47UxGyXn2FM"},"dcId":4}],[":bigint:713147582",{"type":"user","self":false,"contact":false,"mutualContact":false,"deleted":false,"bot":false,"botChatHistory":false,"botNochats":false,"verified":false,"restricted":false,"min":false,"botInlineGeo":false,"support":false,"scam":false,"applyMinPhoto":true,"fake":false,"id":"713147582","accessHash":"-9068816234251792680","firstName":"Hugo","lastName":"Gonçalves","username":"God_Lx","status":"recently","photo":{"date":1700788198,"_":"chatPhoto","isBig":true,"dcId":4,"fileId":"AQADBAADqacxG77EgSoACAEABwMAA77EgSoABNhOIAABrxclggAEHgQ","uniqueFileId":"AQADqacxG77EgSo"},"dcId":4}],["God_Lx",{"type":"user","self":false,"contact":false,"mutualContact":false,"deleted":false,"bot":false,"botChatHistory":false,"botNochats":false,"verified":false,"restricted":false,"min":false,"botInlineGeo":false,"support":false,"scam":false,"applyMinPhoto":true,"fake":false,"id":"713147582","accessHash":"-9068816234251792680","firstName":"Hugo","lastName":"Gonçalves","username":"God_Lx","status":"recently","photo":{"date":1700788198,"_":"chatPhoto","isBig":true,"dcId":4,"fileId":"AQADBAADqacxG77EgSoACAEABwMAA77EgSoABNhOIAABrxclggAEHgQ","uniqueFileId":"AQADqacxG77EgSo"},"dcId":4}],[":bigint:6892133845",{"type":"user","self":false,"contact":false,"mutualContact":false,"deleted":false,"bot":true,"botChatHistory":false,"botNochats":false,"verified":false,"restricted":false,"min":false,"botInlineGeo":false,"support":false,"scam":false,"applyMinPhoto":true,"fake":false,"id":"6892133845","accessHash":"5322164249476448577","firstName":"Fang Fang Kuaci","username":"FangFangKuaciBot","botInfoVersion":2,"photo":{"date":1700788604,"_":"chatPhoto","isBig":true,"dcId":5,"fileId":"AQADBQADdboxG5TYwFUACAEABwMAA9WdzZoBAANBwVPWLyDcSQAEHgQ","uniqueFileId":"AQADdboxG5TYwFU"},"dcId":5}],["FangFangKuaciBot",{"type":"user","self":false,"contact":false,"mutualContact":false,"deleted":false,"bot":true,"botChatHistory":false,"botNochats":false,"verified":false,"restricted":false,"min":false,"botInlineGeo":false,"support":false,"scam":false,"applyMinPhoto":true,"fake":false,"id":"6892133845","accessHash":"5322164249476448577","firstName":"Fang Fang Kuaci","username":"FangFangKuaciBot","botInfoVersion":2,"photo":{"date":1700788604,"_":"chatPhoto","isBig":true,"dcId":5,"fileId":"AQADBQADdboxG5TYwFUACAEABwMAA9WdzZoBAANBwVPWLyDcSQAEHgQ","uniqueFileId":"AQADdboxG5TYwFU"},"dcId":5}],[":bigint:6330855133",{"type":"user","self":false,"contact":false,"mutualContact":false,"deleted":false,"bot":true,"botChatHistory":false,"botNochats":false,"verified":false,"restricted":false,"min":false,"botInlineGeo":false,"support":false,"scam":false,"applyMinPhoto":true,"fake":false,"id":"6330855133","accessHash":"-3823527436485260597","firstName":"Amon Super Badung","username":"amonSuperBadungBot","botInfoVersion":3,"photo":{"date":1700789227,"_":"chatPhoto","isBig":true,"dcId":5,"fileId":"AQADBQADSLcxG3LUSFUACAEABwMAA90uWXkBAAPLClbvDRrwygAEHgQ","uniqueFileId":"AQADSLcxG3LUSFU"},"dcId":5}],["amonSuperBadungBot",{"type":"user","self":false,"contact":false,"mutualContact":false,"deleted":false,"bot":true,"botChatHistory":false,"botNochats":false,"verified":false,"restricted":false,"min":false,"botInlineGeo":false,"support":false,"scam":false,"applyMinPhoto":true,"fake":false,"id":"6330855133","accessHash":"-3823527436485260597","firstName":"Amon Super Badung","username":"amonSuperBadungBot","botInfoVersion":3,"photo":{"date":1700789227,"_":"chatPhoto","isBig":true,"dcId":5,"fileId":"AQADBQADSLcxG3LUSFUACAEABwMAA90uWXkBAAPLClbvDRrwygAEHgQ","uniqueFileId":"AQADSLcxG3LUSFU"},"dcId":5}],[":bigint:753408209",{"type":"user","self":false,"contact":false,"mutualContact":false,"deleted":false,"bot":false,"botChatHistory":false,"botNochats":false,"verified":false,"restricted":false,"min":true,"botInlineGeo":false,"support":false,"scam":false,"applyMinPhoto":false,"fake":false,"id":"753408209","accessHash":"-8403381561558688306","firstName":"Banez 𝕏","status":"recently","photo":{"date":1700790207,"_":"chatPhoto","isBig":true,"dcId":5,"fileId":"AQADBQADPakxG9EY6CwACAEABwMAA9EY6CwABM4dOif-MGGLAAQeBA","uniqueFileId":"AQADPakxG9EY6Cw"},"dcId":5}],[":bigint:-1001262402677",{"type":"supergroup","creator":false,"left":false,"broadcast":false,"verified":false,"megagroup":true,"restricted":false,"signatures":false,"min":true,"scam":false,"hasLink":true,"hasGeo":false,"slowmodeEnabled":false,"callActive":false,"callNotEmpty":false,"fake":false,"gigagroup":false,"noforward":false,"id":"-1001262402677","accessHash":"6665621839550863946","title":"Poco F5 | MARBLE 🇮🇩","username":"PocoF5indo","defaultBannedRights":{"viewMessages":false,"sendMessages":false,"sendMedia":false,"sendStickers":false,"sendGifs":false,"sendGames":false,"sendInline":false,"embedLinks":true,"sendPolls":true,"changeInfo":true,"inviteUsers":true,"pinMessages":true,"untilDate":2147483647},"photo":{"date":1700790207,"_":"chatPhoto","isBig":true,"dcId":5,"fileId":"AQADBQAD-bgxG7aQCFUACAEABwMAA4szHOAW____StqDQb8LgVwABB4E","uniqueFileId":"AQAD-bgxG7aQCFU"},"dcId":5}],["PocoF5indo",{"type":"supergroup","creator":false,"left":false,"broadcast":false,"verified":false,"megagroup":true,"restricted":false,"signatures":false,"min":true,"scam":false,"hasLink":true,"hasGeo":false,"slowmodeEnabled":false,"callActive":false,"callNotEmpty":false,"fake":false,"gigagroup":false,"noforward":false,"id":"-1001262402677","accessHash":"6665621839550863946","title":"Poco F5 | MARBLE 🇮🇩","username":"PocoF5indo","defaultBannedRights":{"viewMessages":false,"sendMessages":false,"sendMedia":false,"sendStickers":false,"sendGifs":false,"sendGames":false,"sendInline":false,"embedLinks":true,"sendPolls":true,"changeInfo":true,"inviteUsers":true,"pinMessages":true,"untilDate":2147483647},"photo":{"date":1700790207,"_":"chatPhoto","isBig":true,"dcId":5,"fileId":"AQADBQAD-bgxG7aQCFUACAEABwMAA4szHOAW____StqDQb8LgVwABB4E","uniqueFileId":"AQAD-bgxG7aQCFU"},"dcId":5}],[":bigint:54394112",{"type":"user","self":false,"contact":false,"mutualContact":false,"deleted":false,"bot":false,"botChatHistory":false,"botNochats":false,"verified":false,"restricted":false,"min":true,"botInlineGeo":false,"support":false,"scam":false,"applyMinPhoto":false,"fake":false,"id":"54394112","accessHash":"-3342943499924110943","firstName":"Andy","status":"recently","photo":{"date":1700789651,"_":"chatPhoto","isBig":true,"dcId":5,"fileId":"AQADBQADwKcxGwAB_T0DAAgBAAcDAAT9PQMABKGB0jaZepvRAAQeBA","uniqueFileId":"AQADwKcxGwAB_T0D"},"dcId":5}],["AndyFaisalAchmad",{"type":"user","self":false,"contact":false,"mutualContact":false,"deleted":false,"bot":false,"botChatHistory":false,"botNochats":false,"verified":false,"restricted":false,"min":false,"botInlineGeo":false,"support":false,"scam":false,"applyMinPhoto":true,"fake":false,"id":"54394112","accessHash":"-7320484439217242460","firstName":"Andy","username":"AndyFaisalAchmad","status":"recently","photo":{"date":1700789619,"_":"chatPhoto","isBig":true,"dcId":5,"fileId":"AQADBQADwKcxGwAB_T0DAAgBAAcDAAT9PQMABKR-rigwamiaAAQeBA","uniqueFileId":"AQADwKcxGwAB_T0D"},"dcId":5}],[":bigint:1934348237",{"type":"user","self":false,"contact":false,"mutualContact":false,"deleted":false,"bot":false,"botChatHistory":false,"botNochats":false,"verified":false,"restricted":false,"min":true,"botInlineGeo":false,"support":false,"scam":false,"applyMinPhoto":false,"fake":false,"id":"1934348237","accessHash":"4136132452349030356","firstName":"𝗞𝘂𝗰𝗶𝗻𝗴 𝗔𝗯𝘂","status":"recently","photo":{"date":1700789642,"_":"chatPhoto","isBig":true,"dcId":5,"fileId":"AQADBQADw7wxG2Ow0VQACAEABwMAA83PS3MABNSvOh6NfmY5AAQeBA","uniqueFileId":"AQADw7wxG2Ow0VQ"},"dcId":5}],[":bigint:609517172",{"type":"user","self":false,"contact":false,"mutualContact":false,"deleted":false,"bot":true,"botChatHistory":true,"botNochats":false,"verified":false,"restricted":false,"min":true,"botInlineGeo":false,"support":false,"scam":false,"applyMinPhoto":true,"fake":false,"id":"609517172","accessHash":"3296789432007109466","firstName":"Rose","username":"MissRose_bot","botInfoVersion":19,"photo":{"date":1700789699,"_":"chatPhoto","isBig":true,"dcId":4,"fileId":"AQADBAADq6cxG3R-VCQACAEABwMAA3R-VCQABFqrC3KFjMAtAAQeBA","uniqueFileId":"AQADq6cxG3R-VCQ"},"dcId":4}],["MissRose_bot",{"type":"user","self":false,"contact":false,"mutualContact":false,"deleted":false,"bot":true,"botChatHistory":true,"botNochats":false,"verified":false,"restricted":false,"min":true,"botInlineGeo":false,"support":false,"scam":false,"applyMinPhoto":true,"fake":false,"id":"609517172","accessHash":"3296789432007109466","firstName":"Rose","username":"MissRose_bot","botInfoVersion":19,"photo":{"date":1700789699,"_":"chatPhoto","isBig":true,"dcId":4,"fileId":"AQADBAADq6cxG3R-VCQACAEABwMAA3R-VCQABFqrC3KFjMAtAAQeBA","uniqueFileId":"AQADq6cxG3R-VCQ"},"dcId":4}],[":bigint:2115011716",{"type":"user","self":false,"contact":false,"mutualContact":false,"deleted":false,"bot":false,"botChatHistory":false,"botNochats":false,"verified":false,"restricted":false,"min":false,"botInlineGeo":false,"support":false,"scam":false,"applyMinPhoto":true,"fake":false,"id":"2115011716","accessHash":"62029370850782647","firstName":"スティーブン","username":"ryzenforce","status":"recently","photo":{"date":1700789652,"_":"chatPhoto","isBig":true,"dcId":5,"fileId":"AQADBQADWbwxGxUOmVYACAEABwMAA4SEEH4ABLetM1diX9wABR4E","uniqueFileId":"AQADWbwxGxUOmVY"},"dcId":5}],["ryzenforce",{"type":"user","self":false,"contact":false,"mutualContact":false,"deleted":false,"bot":false,"botChatHistory":false,"botNochats":false,"verified":false,"restricted":false,"min":false,"botInlineGeo":false,"support":false,"scam":false,"applyMinPhoto":true,"fake":false,"id":"2115011716","accessHash":"62029370850782647","firstName":"スティーブン","username":"ryzenforce","status":"recently","photo":{"date":1700789652,"_":"chatPhoto","isBig":true,"dcId":5,"fileId":"AQADBQADWbwxGxUOmVYACAEABwMAA4SEEH4ABLetM1diX9wABR4E","uniqueFileId":"AQADWbwxGxUOmVY"},"dcId":5}],[":bigint:6516245543",{"type":"user","self":false,"contact":false,"mutualContact":false,"deleted":false,"bot":true,"botChatHistory":false,"botNochats":false,"verified":false,"restricted":false,"min":false,"botInlineGeo":false,"support":false,"scam":false,"applyMinPhoto":true,"fake":false,"id":"6516245543","accessHash":"5529897814713726820","firstName":"O P A N K","username":"OpankGemoyBOT","botInfoVersion":2,"photo":{"date":1700790217,"_":"chatPhoto","isBig":true,"dcId":5,"fileId":"AQADBQADZ7YxG3KLAVUACAEABwMAAycEZoQBAANkdziKwyS-TAAEHgQ","uniqueFileId":"AQADZ7YxG3KLAVU"},"dcId":5}],["OpankGemoyBOT",{"type":"user","self":false,"contact":false,"mutualContact":false,"deleted":false,"bot":true,"botChatHistory":false,"botNochats":false,"verified":false,"restricted":false,"min":false,"botInlineGeo":false,"support":false,"scam":false,"applyMinPhoto":true,"fake":false,"id":"6516245543","accessHash":"5529897814713726820","firstName":"O P A N K","username":"OpankGemoyBOT","botInfoVersion":2,"photo":{"date":1700790217,"_":"chatPhoto","isBig":true,"dcId":5,"fileId":"AQADBQADZ7YxG3KLAVUACAEABwMAAycEZoQBAANkdziKwyS-TAAEHgQ","uniqueFileId":"AQADZ7YxG3KLAVU"},"dcId":5}]]